pyThorlabsTC300/TC300COMMANDLIB_win32.dll
pyThorlabsTC300/TC300COMMANDLIB_win64.dll
pyThorlabsTC300/TC300_COMMAND_LIB.py
pyThorlabsTC300/TC300_COMMAND_LIB_EXAMPLE.py
pyThorlabsTC300/__init__.py
pyThorlabsTC300/config.json
pyThorlabsTC300/driver.py
pyThorlabsTC300/main.py
pyThorlabsTC300/graphics/pause.png
pyThorlabsTC300/graphics/play.png
pyThorlabsTC300/graphics/refresh.png
pyThorlabsTC300/graphics/stop.png
pyThorlabsTC300-0.3.dist-info/METADATA
pyThorlabsTC300-0.3.dist-info/WHEEL
pyThorlabsTC300-0.3.dist-info/entry_points.txt
pyThorlabsTC300-0.3.dist-info/top_level.txt
pyThorlabsTC300-0.3.dist-info/RECORD
