Metadata-Version: 2.1
Name: pyThorlabsTC300
Version: 0.3
Summary: A python library/GUI to access and control the TC300 Temperature Controller of Thorlabs.
Home-page: https://github.com/MicheleCotrufo/
Author: Michele Cotrufo
Author-email: michele.cotrufo@gmail.com
License: MIT
